<?xml version="1.1" encoding="UTF-8" standalone="no"?>
<databaseChangeLog xmlns="http://www.liquibase.org/xml/ns/dbchangelog" xmlns:ext="http://www.liquibase.org/xml/ns/dbchangelog-ext" xmlns:pro="http://www.liquibase.org/xml/ns/pro" xmlns:xsi="http://www.w3.org/2001/XMLSchema-instance" xsi:schemaLocation="http://www.liquibase.org/xml/ns/dbchangelog-ext http://www.liquibase.org/xml/ns/dbchangelog/dbchangelog-ext.xsd http://www.liquibase.org/xml/ns/pro http://www.liquibase.org/xml/ns/pro/liquibase-pro-latest.xsd http://www.liquibase.org/xml/ns/dbchangelog http://www.liquibase.org/xml/ns/dbchangelog/dbchangelog-latest.xsd">
    <changeSet author="mancinijor (generated)" id="1717677691736-1">
        <createTable tableName="message_template">
            <column name="id" type="UUID">
                <constraints nullable="false" primaryKey="true" primaryKeyName="message_templatePK"/>
            </column>
            <column name="key_" type="VARCHAR(255)"/>
            <column name="message" type="VARCHAR(255)">
                <constraints nullable="false"/>
            </column>
        </createTable>
    </changeSet>
    <changeSet author="mancinijor (generated)" id="1717677691736-2">
        <createTable tableName="report_node">
            <column name="id" type="UUID">
                <constraints nullable="false" primaryKey="true" primaryKeyName="report_nodePK"/>
            </column>
            <column name="nanos" type="BIGINT"/>
            <column name="message_template_id" type="UUID"/>
            <column name="parent_id" type="UUID"/>
        </createTable>
    </changeSet>
    <changeSet author="mancinijor (generated)" id="1717677691736-3">
        <createTable tableName="report_node_values">
            <column name="report_node_id" type="UUID">
                <constraints nullable="false"/>
            </column>
            <column name="key_" type="VARCHAR(255)">
                <constraints nullable="false"/>
            </column>
            <column name="local_value_type" type="TINYINT"/>
            <column name="value_" type="VARCHAR(255)">
                <constraints nullable="false"/>
            </column>
            <column name="value_type" type="VARCHAR(255)"/>
        </createTable>
    </changeSet>
    <changeSet author="mancinijor (generated)" id="1717677691736-4">
        <createTable tableName="severity_level">
            <column name="report_node_id" type="UUID">
                <constraints nullable="false"/>
            </column>
            <column name="severities" type="VARCHAR(255)"/>
        </createTable>
    </changeSet>
    <changeSet author="mancinijor (generated)" id="1717677691736-5">
        <createIndex indexName="report_node_severity_idx" tableName="severity_level">
            <column name="report_node_id"/>
        </createIndex>
    </changeSet>
    <changeSet author="mancinijor (generated)" id="1717677691736-6">
        <createIndex indexName="report_node_value_idx" tableName="report_node_values">
            <column name="report_node_id"/>
        </createIndex>
    </changeSet>
    <changeSet author="mancinijor (generated)" id="1717677691736-7">
        <addForeignKeyConstraint baseColumnNames="message_template_id" baseTableName="report_node" constraintName="FK342nc24j9vhueopm2t0q4ltf1" deferrable="false" initiallyDeferred="false" referencedColumnNames="id" referencedTableName="message_template" validate="true"/>
    </changeSet>
    <changeSet author="mancinijor (generated)" id="1717677691736-8">
        <addForeignKeyConstraint baseColumnNames="parent_id" baseTableName="report_node" constraintName="FKbj6ti2m0o5faxme65mv8aguj5" deferrable="false" initiallyDeferred="false" referencedColumnNames="id" referencedTableName="report_node" validate="true"/>
    </changeSet>
    <changeSet author="mancinijor (generated)" id="1717677691736-9">
        <addForeignKeyConstraint baseColumnNames="report_node_id" baseTableName="severity_level" constraintName="report_node_severity_fk" deferrable="false" initiallyDeferred="false" referencedColumnNames="id" referencedTableName="report_node" validate="true"/>
    </changeSet>
    <changeSet author="mancinijor (generated)" id="1717677691736-10">
        <addForeignKeyConstraint baseColumnNames="report_node_id" baseTableName="report_node_values" constraintName="report_node_value_fk" deferrable="false" initiallyDeferred="false" referencedColumnNames="id" referencedTableName="report_node" validate="true"/>
    </changeSet>
    <changeSet author="mancinijor (generated)" id="1717677691736-11">
        <dropForeignKeyConstraint baseTableName="TREE_REPORT" constraintName="REPORT_ID_FK_CONSTRAINT"/>
    </changeSet>
    <changeSet author="mancinijor (generated)" id="1717677691736-12">
        <dropForeignKeyConstraint baseTableName="REPORT_ELEMENT" constraintName="treeReportElement_id_fk_constraint"/>
    </changeSet>
    <changeSet author="mancinijor (generated)" id="1717677691736-13">
        <dropForeignKeyConstraint baseTableName="TREE_REPORT_ENTITY_VALUES" constraintName="treeReportEmbeddable_name_fk"/>
    </changeSet>
    <changeSet author="mancinijor (generated)" id="1717677691736-14">
        <dropForeignKeyConstraint baseTableName="REPORT_ELEMENT_ENTITY_VALUES" constraintName="treeReportEmbeddable_subReports_fk"/>
    </changeSet>
    <changeSet author="mancinijor (generated)" id="1717677691736-15">
        <dropForeignKeyConstraint baseTableName="TREE_REPORT_ENTITY_DICTIONARY" constraintName="treeReportEntity_dictionary_fk"/>
    </changeSet>
    <changeSet author="mancinijor (generated)" id="1717677691736-16">
        <dropForeignKeyConstraint baseTableName="TREE_REPORT" constraintName="treeReport_id_fk_constraint"/>
    </changeSet>
    <changeSet author="mancinijor (generated)" id="1717677691736-17">
        <dropTable tableName="REPORT"/>
    </changeSet>
    <changeSet author="mancinijor (generated)" id="1717677691736-18">
        <dropTable tableName="REPORT_ELEMENT"/>
    </changeSet>
    <changeSet author="mancinijor (generated)" id="1717677691736-19">
        <dropTable tableName="REPORT_ELEMENT_ENTITY_VALUES"/>
    </changeSet>
    <changeSet author="mancinijor (generated)" id="1717677691736-20">
        <dropTable tableName="TREE_REPORT"/>
    </changeSet>
    <changeSet author="mancinijor (generated)" id="1717677691736-21">
        <dropTable tableName="TREE_REPORT_ENTITY_DICTIONARY"/>
    </changeSet>
    <changeSet author="mancinijor (generated)" id="1717677691736-22">
        <dropTable tableName="TREE_REPORT_ENTITY_VALUES"/>
    </changeSet>
</databaseChangeLog>
